python_builtins/__init__.py
python_builtins/enumerate.py
python_builtins-0.1.0.dist-info/METADATA
python_builtins-0.1.0.dist-info/WHEEL
python_builtins-0.1.0.dist-info/RECORD
